Workbook
Name aporte: App!$E$17
Name patrimonio: App!$E$20
Name qto_anos: App!$E$18
Name rendimento_carteira: App!$E$8
Name salario: App!$E$7
Name sugestao_investimento: App!$E$9
Name taxa_mensal: App!$E$19

Sheet App
C6: CONFIGURAÇÕES
C7: Salário | E7: 5000
C8: Rendimento Carteira | E8: 0.01
C9: Sugestão de investimento | E9: =E7*30% -> 1500
C16: INVESTIMENTO MENSAL
C17: Quanto investir por mês? | E17: 750
C18: Por quantos anos? | E18: 5
C19: Taxa de rendimento mensal? | E19: 0.01079
C20: Patrimônio acumulado? | E20: =FV(taxa_mensal,qto_anos*12,aporte*-1) -> 62832.685
C21: Dividendos mensais? | E21: =patrimonio*rendimento_carteira -> 628.32685
C24: Cenários | E24: Dividendos
B25: 2 | C25: Quanto em 2 anos? | D25: =FV($E$19,$B25*12,E17*-1) -> 20420.72 | E25: =D25*rendimento_carteira -> 204.2072
B26: 5 | C26: Quanto em 5 anos? | D26: =FV($E$19,$B26*12,E17*-1) -> 62832.685 | E26: =D26*rendimento_carteira -> 628.32685
B27: 10 | C27: Quanto em 10 anos? | D27: =FV($E$19,$B27*12,E17*-1) -> 182463.16 | E27: =D27*rendimento_carteira -> 1824.6316
B28: 20 | C28: Quanto em 20 anos? | D28: =FV($E$19,$B28*12,E17*-1) -> 843898.8 | E28: =D28*rendimento_carteira -> 8438.988
B29: 30 | C29: Quanto em 30 anos? | D29: =FV($E$19,$B29*12,E17*-1) -> 3241627.2 | E29: =D29*rendimento_carteira -> 32416.272
C32: Perfil | E32: Conservador
C33: VALOR A SER INVESTIDO POR MÊS | E33: 500
C36: TIPO DE FII | D36: PERCENTUAL SUGERIDO | E36: VALORES
C37: PAPEL | D37: =VLOOKUP($E$32&"-"&C37,Planilha2!$A:$D,4,FALSE) -> 0.3 | E37: =D37*$E$33 -> 150
C38: TIJOLO | D38: =VLOOKUP($E$32&"-"&C38,Planilha2!$A:$D,4,FALSE) -> 0.5 | E38: =D38*$E$33 -> 250
C39: HÍBRIDOS | D39: =VLOOKUP($E$32&"-"&C39,Planilha2!$A:$D,4,FALSE) -> 0.1 | E39: =D39*$E$33 -> 50
C40: FOFS | D40: =VLOOKUP($E$32&"-"&C40,Planilha2!$A:$D,4,FALSE) -> 0.1 | E40: =D40*$E$33 -> 50
C41: DESENVOLVIMENTO | D41: =VLOOKUP($E$32&"-"&C41,Planilha2!$A:$D,4,FALSE) -> 0 | E41: =D41*$E$33 -> 0
C42: HOTELARIAS | D42: =VLOOKUP($E$32&"-"&C42,Planilha2!$A:$D,4,FALSE) -> 0 | E42: =D42*$E$33 -> 0
E43: =SUM(E37:E42) -> 500

Sheet Planilha2
A2: CHAVE | B2: PERFIL | C2: TIPO DE FII | D2: %
A3: =$B$3&"-"&C3 -> Conservador-PAPEL | B3: Conservador | C3: PAPEL | D3: 0.3 | H3: %
A4: =$B$3&"-"&C4 -> Conservador-TIJOLO | B4: Conservador | C4: TIJOLO | D4: 0.5 | G4: Moderado-TIJOLO | H4: =VLOOKUP(G4,$A:$D,4,FALSE) -> 0.35
A5: =$B$3&"-"&C5 -> Conservador-HÍBRIDOS | B5: Conservador | C5: HÍBRIDOS | D5: 0.1
A6: =$B$3&"-"&C6 -> Conservador-FOFS | B6: Conservador | C6: FOFS | D6: 0.1
A7: =$B$3&"-"&C7 -> Conservador-DESENVOLVIMENTO | B7: Conservador | C7: DESENVOLVIMENTO | D7: 0
A8: =$B$3&"-"&C8 -> Conservador-HOTELARIAS | B8: Conservador | C8: HOTELARIAS | D8: 0
A9: =$B$9&"-"&C9 -> Moderado-PAPEL | B9: Moderado | C9: PAPEL | D9: 0.32
A10: =$B$9&"-"&C10 -> Moderado-TIJOLO | B10: Moderado | C10: TIJOLO | D10: 0.35
A11: =$B$9&"-"&C11 -> Moderado-HÍBRIDOS | B11: Moderado | C11: HÍBRIDOS | D11: 0.08
A12: =$B$9&"-"&C12 -> Moderado-FOFS | B12: Moderado | C12: FOFS | D12: 0.05
A13: =$B$9&"-"&C13 -> Moderado-DESENVOLVIMENTO | B13: Moderado | C13: DESENVOLVIMENTO | D13: 0.1
A14: =$B$9&"-"&C14 -> Moderado-HOTELARIAS | B14: Moderado | C14: HOTELARIAS | D14: 0.1
A15: =$B$15&"-"&C15 -> Agressivo-PAPEL | B15: Agressivo | C15: PAPEL | D15: 0.5
A16: =$B$15&"-"&C16 -> Agressivo-TIJOLO | B16: Agressivo | C16: TIJOLO | D16: 0.1
A17: =$B$15&"-"&C17 -> Agressivo-HÍBRIDOS | B17: Agressivo | C17: HÍBRIDOS | D17: 0.05
A18: =$B$15&"-"&C18 -> Agressivo-FOFS | B18: Agressivo | C18: FOFS | D18: 0.05
A19: =$B$15&"-"&C19 -> Agressivo-DESENVOLVIMENTO | B19: Agressivo | C19: DESENVOLVIMENTO | D19: 0.2
A20: =$B$15&"-"&C20 -> Agressivo-HOTELARIAS | B20: Agressivo | C20: HOTELARIAS | D20: 0.1
